<?xml version="1.0" encoding="UTF-8"?>
<annotation>
    <folder>ar0001_kakaku_kB0000104974.jpg</folder>
    <filename>000332.jpg</filename>
    <source>
        <database>The VOC2007 Database</database>
        <annotation>PASCAL VOC2007</annotation>
    </source>
    <size>
        <width>512</width>
        <height>512</height>
        <depth>3</depth>
    </size>
    <object>
        <name>Character</name>
        <occluded>0</occluded>
        <bndbox>
            <xmin>89</xmin>
            <ymin>15</ymin>
            <xmax>158</xmax>
            <ymax>72</ymax>
        </bndbox>
    </object>
    <object>
        <name>Character</name>
        <occluded>0</occluded>
        <bndbox>
            <xmin>158</xmin>
            <ymin>12</ymin>
            <xmax>247</xmax>
            <ymax>74</ymax>
        </bndbox>
    </object>
    <object>
        <name>Character</name>
        <occluded>0</occluded>
        <bndbox>
            <xmin>247</xmin>
            <ymin>12</ymin>
            <xmax>329</xmax>
            <ymax>72</ymax>
        </bndbox>
    </object>
    <object>
        <name>Character</name>
        <occluded>0</occluded>
        <bndbox>
            <xmin>328</xmin>
            <ymin>13</ymin>
            <xmax>421</xmax>
            <ymax>71</ymax>
        </bndbox>
    </object>
    <object>
        <name>Character</name>
        <occluded>0</occluded>
        <bndbox>
            <xmin>47</xmin>
            <ymin>79</ymin>
            <xmax>95</xmax>
            <ymax>120</ymax>
        </bndbox>
    </object>
    <object>
        <name>Character</name>
        <occluded>0</occluded>
        <bndbox>
            <xmin>94</xmin>
            <ymin>79</ymin>
            <xmax>156</xmax>
            <ymax>120</ymax>
        </bndbox>
    </object>
    <object>
        <name>Character</name>
        <occluded>0</occluded>
        <bndbox>
            <xmin>157</xmin>
            <ymin>81</ymin>
            <xmax>212</xmax>
            <ymax>116</ymax>
        </bndbox>
    </object>
    <object>
        <name>Character</name>
        <occluded>0</occluded>
        <bndbox>
            <xmin>214</xmin>
            <ymin>80</ymin>
            <xmax>261</xmax>
            <ymax>118</ymax>
        </bndbox>
    </object>
    <object>
        <name>Character</name>
        <occluded>0</occluded>
        <bndbox>
            <xmin>260</xmin>
            <ymin>84</ymin>
            <xmax>308</xmax>
            <ymax>114</ymax>
        </bndbox>
    </object>
    <object>
        <name>Character</name>
        <occluded>0</occluded>
        <bndbox>
            <xmin>310</xmin>
            <ymin>79</ymin>
            <xmax>362</xmax>
            <ymax>117</ymax>
        </bndbox>
    </object>
    <object>
        <name>Character</name>
        <occluded>0</occluded>
        <bndbox>
            <xmin>360</xmin>
            <ymin>79</ymin>
            <xmax>412</xmax>
            <ymax>115</ymax>
        </bndbox>
    </object>
    <object>
        <name>Character</name>
        <occluded>0</occluded>
        <bndbox>
            <xmin>416</xmin>
            <ymin>82</ymin>
            <xmax>464</xmax>
            <ymax>117</ymax>
        </bndbox>
    </object>
</annotation>
