<?xml version="1.0" encoding="UTF-8"?>
<annotation>
    <folder>ar0001_kakaku_kB0000138841.jpg</folder>
    <filename>000964.jpg</filename>
    <source>
        <database>The VOC2007 Database</database>
        <annotation>PASCAL VOC2007</annotation>
    </source>
    <size>
        <width>512</width>
        <height>512</height>
        <depth>3</depth>
    </size>
    <object>
        <name>Character</name>
        <occluded>0</occluded>
        <bndbox>
            <xmin>373</xmin>
            <ymin>81</ymin>
            <xmax>461</xmax>
            <ymax>142</ymax>
        </bndbox>
    </object>
    <object>
        <name>Character</name>
        <occluded>0</occluded>
        <bndbox>
            <xmin>377</xmin>
            <ymin>146</ymin>
            <xmax>454</xmax>
            <ymax>198</ymax>
        </bndbox>
    </object>
    <object>
        <name>Character</name>
        <occluded>0</occluded>
        <bndbox>
            <xmin>376</xmin>
            <ymin>209</ymin>
            <xmax>454</xmax>
            <ymax>260</ymax>
        </bndbox>
    </object>
    <object>
        <name>Character</name>
        <occluded>0</occluded>
        <bndbox>
            <xmin>381</xmin>
            <ymin>268</ymin>
            <xmax>454</xmax>
            <ymax>320</ymax>
        </bndbox>
    </object>
    <object>
        <name>Character</name>
        <occluded>0</occluded>
        <bndbox>
            <xmin>387</xmin>
            <ymin>325</ymin>
            <xmax>450</xmax>
            <ymax>384</ymax>
        </bndbox>
    </object>
    <object>
        <name>Character</name>
        <occluded>0</occluded>
        <bndbox>
            <xmin>387</xmin>
            <ymin>388</ymin>
            <xmax>455</xmax>
            <ymax>444</ymax>
        </bndbox>
    </object>
    <object>
        <name>Character</name>
        <occluded>0</occluded>
        <bndbox>
            <xmin>273</xmin>
            <ymin>205</ymin>
            <xmax>368</xmax>
            <ymax>266</ymax>
        </bndbox>
    </object>
    <object>
        <name>Character</name>
        <occluded>0</occluded>
        <bndbox>
            <xmin>284</xmin>
            <ymin>266</ymin>
            <xmax>358</xmax>
            <ymax>322</ymax>
        </bndbox>
    </object>
    <object>
        <name>Character</name>
        <occluded>0</occluded>
        <bndbox>
            <xmin>281</xmin>
            <ymin>327</ymin>
            <xmax>365</xmax>
            <ymax>383</ymax>
        </bndbox>
    </object>
    <object>
        <name>Character</name>
        <occluded>0</occluded>
        <bndbox>
            <xmin>290</xmin>
            <ymin>386</ymin>
            <xmax>362</xmax>
            <ymax>446</ymax>
        </bndbox>
    </object>
</annotation>
