<?xml version="1.0" encoding="UTF-8"?>
<annotation>
    <folder>ar0001_kakaku_kB0000142449.jpg</folder>
    <filename>001536.jpg</filename>
    <source>
        <database>The VOC2007 Database</database>
        <annotation>PASCAL VOC2007</annotation>
    </source>
    <size>
        <width>512</width>
        <height>512</height>
        <depth>3</depth>
    </size>
    <object>
        <name>Character</name>
        <occluded>0</occluded>
        <bndbox>
            <xmin>11</xmin>
            <ymin>130</ymin>
            <xmax>83</xmax>
            <ymax>182</ymax>
        </bndbox>
    </object>
    <object>
        <name>Character</name>
        <occluded>0</occluded>
        <bndbox>
            <xmin>83</xmin>
            <ymin>128</ymin>
            <xmax>155</xmax>
            <ymax>182</ymax>
        </bndbox>
    </object>
    <object>
        <name>Character</name>
        <occluded>0</occluded>
        <bndbox>
            <xmin>154</xmin>
            <ymin>142</ymin>
            <xmax>212</xmax>
            <ymax>182</ymax>
        </bndbox>
    </object>
    <object>
        <name>Character</name>
        <occluded>0</occluded>
        <bndbox>
            <xmin>15</xmin>
            <ymin>183</ymin>
            <xmax>90</xmax>
            <ymax>240</ymax>
        </bndbox>
    </object>
    <object>
        <name>Character</name>
        <occluded>0</occluded>
        <bndbox>
            <xmin>91</xmin>
            <ymin>184</ymin>
            <xmax>172</xmax>
            <ymax>238</ymax>
        </bndbox>
    </object>
    <object>
        <name>Character</name>
        <occluded>0</occluded>
        <bndbox>
            <xmin>9</xmin>
            <ymin>243</ymin>
            <xmax>108</xmax>
            <ymax>313</ymax>
        </bndbox>
    </object>
    <object>
        <name>Character</name>
        <occluded>0</occluded>
        <bndbox>
            <xmin>115</xmin>
            <ymin>243</ymin>
            <xmax>212</xmax>
            <ymax>313</ymax>
        </bndbox>
    </object>
    <object>
        <name>Character</name>
        <occluded>0</occluded>
        <bndbox>
            <xmin>217</xmin>
            <ymin>242</ymin>
            <xmax>316</xmax>
            <ymax>313</ymax>
        </bndbox>
    </object>
    <object>
        <name>Character</name>
        <occluded>0</occluded>
        <bndbox>
            <xmin>11</xmin>
            <ymin>314</ymin>
            <xmax>48</xmax>
            <ymax>339</ymax>
        </bndbox>
    </object>
    <object>
        <name>Character</name>
        <occluded>0</occluded>
        <bndbox>
            <xmin>50</xmin>
            <ymin>314</ymin>
            <xmax>83</xmax>
            <ymax>339</ymax>
        </bndbox>
    </object>
    <object>
        <name>Character</name>
        <occluded>0</occluded>
        <bndbox>
            <xmin>84</xmin>
            <ymin>313</ymin>
            <xmax>119</xmax>
            <ymax>339</ymax>
        </bndbox>
    </object>
    <object>
        <name>Character</name>
        <occluded>0</occluded>
        <bndbox>
            <xmin>119</xmin>
            <ymin>314</ymin>
            <xmax>155</xmax>
            <ymax>339</ymax>
        </bndbox>
    </object>
    <object>
        <name>Character</name>
        <occluded>0</occluded>
        <bndbox>
            <xmin>157</xmin>
            <ymin>314</ymin>
            <xmax>193</xmax>
            <ymax>340</ymax>
        </bndbox>
    </object>
    <object>
        <name>Character</name>
        <occluded>0</occluded>
        <bndbox>
            <xmin>194</xmin>
            <ymin>313</ymin>
            <xmax>226</xmax>
            <ymax>339</ymax>
        </bndbox>
    </object>
</annotation>
