<?xml version="1.0" encoding="UTF-8"?>
<annotation>
    <folder>ar0001_kakaku_kB0000142554.jpg</folder>
    <filename>001556.jpg</filename>
    <source>
        <database>The VOC2007 Database</database>
        <annotation>PASCAL VOC2007</annotation>
    </source>
    <size>
        <width>512</width>
        <height>512</height>
        <depth>3</depth>
    </size>
    <object>
        <name>Character</name>
        <occluded>0</occluded>
        <bndbox>
            <xmin>122</xmin>
            <ymin>9</ymin>
            <xmax>215</xmax>
            <ymax>78</ymax>
        </bndbox>
    </object>
    <object>
        <name>Character</name>
        <occluded>0</occluded>
        <bndbox>
            <xmin>219</xmin>
            <ymin>10</ymin>
            <xmax>310</xmax>
            <ymax>76</ymax>
        </bndbox>
    </object>
    <object>
        <name>Character</name>
        <occluded>0</occluded>
        <bndbox>
            <xmin>314</xmin>
            <ymin>12</ymin>
            <xmax>396</xmax>
            <ymax>74</ymax>
        </bndbox>
    </object>
    <object>
        <name>Character</name>
        <occluded>0</occluded>
        <bndbox>
            <xmin>401</xmin>
            <ymin>8</ymin>
            <xmax>499</xmax>
            <ymax>77</ymax>
        </bndbox>
    </object>
    <object>
        <name>Character</name>
        <occluded>0</occluded>
        <bndbox>
            <xmin>409</xmin>
            <ymin>82</ymin>
            <xmax>491</xmax>
            <ymax>143</ymax>
        </bndbox>
    </object>
    <object>
        <name>Character</name>
        <occluded>0</occluded>
        <bndbox>
            <xmin>416</xmin>
            <ymin>147</ymin>
            <xmax>490</xmax>
            <ymax>204</ymax>
        </bndbox>
    </object>
    <object>
        <name>Character</name>
        <occluded>0</occluded>
        <bndbox>
            <xmin>409</xmin>
            <ymin>208</ymin>
            <xmax>499</xmax>
            <ymax>266</ymax>
        </bndbox>
    </object>
    <object>
        <name>Character</name>
        <occluded>0</occluded>
        <bndbox>
            <xmin>410</xmin>
            <ymin>272</ymin>
            <xmax>488</xmax>
            <ymax>336</ymax>
        </bndbox>
    </object>
</annotation>
