<?xml version="1.0" encoding="UTF-8"?>
<annotation>
    <folder>ar0001_kakaku_kB0000150332.jpg</folder>
    <filename>002561.jpg</filename>
    <source>
        <database>The VOC2007 Database</database>
        <annotation>PASCAL VOC2007</annotation>
    </source>
    <size>
        <width>512</width>
        <height>512</height>
        <depth>3</depth>
    </size>
    <object>
        <name>Character</name>
        <occluded>0</occluded>
        <bndbox>
            <xmin>15</xmin>
            <ymin>13</ymin>
            <xmax>142</xmax>
            <ymax>81</ymax>
        </bndbox>
    </object>
    <object>
        <name>Character</name>
        <occluded>0</occluded>
        <bndbox>
            <xmin>16</xmin>
            <ymin>84</ymin>
            <xmax>144</xmax>
            <ymax>150</ymax>
        </bndbox>
    </object>
    <object>
        <name>Character</name>
        <occluded>0</occluded>
        <bndbox>
            <xmin>13</xmin>
            <ymin>155</ymin>
            <xmax>151</xmax>
            <ymax>221</ymax>
        </bndbox>
    </object>
    <object>
        <name>Character</name>
        <occluded>0</occluded>
        <bndbox>
            <xmin>16</xmin>
            <ymin>221</ymin>
            <xmax>146</xmax>
            <ymax>289</ymax>
        </bndbox>
    </object>
    <object>
        <name>Character</name>
        <occluded>0</occluded>
        <bndbox>
            <xmin>15</xmin>
            <ymin>291</ymin>
            <xmax>148</xmax>
            <ymax>360</ymax>
        </bndbox>
    </object>
</annotation>
