<?xml version="1.0" encoding="UTF-8"?>
<annotation>
    <folder>ar0001_kakaku_kB0000150980.jpg</folder>
    <filename>002831.jpg</filename>
    <source>
        <database>The VOC2007 Database</database>
        <annotation>PASCAL VOC2007</annotation>
    </source>
    <size>
        <width>512</width>
        <height>512</height>
        <depth>3</depth>
    </size>
    <object>
        <name>Character</name>
        <occluded>0</occluded>
        <bndbox>
            <xmin>262</xmin>
            <ymin>81</ymin>
            <xmax>311</xmax>
            <ymax>110</ymax>
        </bndbox>
    </object>
    <object>
        <name>Character</name>
        <occluded>0</occluded>
        <bndbox>
            <xmin>259</xmin>
            <ymin>110</ymin>
            <xmax>311</xmax>
            <ymax>139</ymax>
        </bndbox>
    </object>
    <object>
        <name>Character</name>
        <occluded>0</occluded>
        <bndbox>
            <xmin>259</xmin>
            <ymin>139</ymin>
            <xmax>312</xmax>
            <ymax>168</ymax>
        </bndbox>
    </object>
    <object>
        <name>Character</name>
        <occluded>0</occluded>
        <bndbox>
            <xmin>259</xmin>
            <ymin>166</ymin>
            <xmax>312</xmax>
            <ymax>194</ymax>
        </bndbox>
    </object>
    <object>
        <name>Character</name>
        <occluded>0</occluded>
        <bndbox>
            <xmin>266</xmin>
            <ymin>192</ymin>
            <xmax>307</xmax>
            <ymax>214</ymax>
        </bndbox>
    </object>
    <object>
        <name>Character</name>
        <occluded>0</occluded>
        <bndbox>
            <xmin>259</xmin>
            <ymin>213</ymin>
            <xmax>313</xmax>
            <ymax>235</ymax>
        </bndbox>
    </object>
    <object>
        <name>Character</name>
        <occluded>0</occluded>
        <bndbox>
            <xmin>263</xmin>
            <ymin>238</ymin>
            <xmax>308</xmax>
            <ymax>267</ymax>
        </bndbox>
    </object>
    <object>
        <name>Character</name>
        <occluded>0</occluded>
        <bndbox>
            <xmin>259</xmin>
            <ymin>266</ymin>
            <xmax>311</xmax>
            <ymax>295</ymax>
        </bndbox>
    </object>
    <object>
        <name>Character</name>
        <occluded>0</occluded>
        <bndbox>
            <xmin>258</xmin>
            <ymin>297</ymin>
            <xmax>311</xmax>
            <ymax>322</ymax>
        </bndbox>
    </object>
    <object>
        <name>Character</name>
        <occluded>0</occluded>
        <bndbox>
            <xmin>262</xmin>
            <ymin>323</ymin>
            <xmax>308</xmax>
            <ymax>351</ymax>
        </bndbox>
    </object>
    <object>
        <name>Character</name>
        <occluded>0</occluded>
        <bndbox>
            <xmin>262</xmin>
            <ymin>350</ymin>
            <xmax>307</xmax>
            <ymax>379</ymax>
        </bndbox>
    </object>
</annotation>
