<?xml version="1.0" encoding="UTF-8"?>
<annotation>
    <folder>ar0001_kakaku_kB0000151095.jpg</folder>
    <filename>002899.jpg</filename>
    <source>
        <database>The VOC2007 Database</database>
        <annotation>PASCAL VOC2007</annotation>
    </source>
    <size>
        <width>512</width>
        <height>512</height>
        <depth>3</depth>
    </size>
    <object>
        <name>Character</name>
        <occluded>0</occluded>
        <bndbox>
            <xmin>8</xmin>
            <ymin>98</ymin>
            <xmax>129</xmax>
            <ymax>184</ymax>
        </bndbox>
    </object>
    <object>
        <name>Character</name>
        <occluded>0</occluded>
        <bndbox>
            <xmin>129</xmin>
            <ymin>97</ymin>
            <xmax>251</xmax>
            <ymax>184</ymax>
        </bndbox>
    </object>
    <object>
        <name>Character</name>
        <occluded>0</occluded>
        <bndbox>
            <xmin>251</xmin>
            <ymin>98</ymin>
            <xmax>368</xmax>
            <ymax>183</ymax>
        </bndbox>
    </object>
    <object>
        <name>Character</name>
        <occluded>0</occluded>
        <bndbox>
            <xmin>371</xmin>
            <ymin>100</ymin>
            <xmax>490</xmax>
            <ymax>182</ymax>
        </bndbox>
    </object>
</annotation>
