<?xml version="1.0" encoding="UTF-8"?>
<annotation>
    <folder>ar0001_kakaku_kB0000151428.jpg</folder>
    <filename>003172.jpg</filename>
    <source>
        <database>The VOC2007 Database</database>
        <annotation>PASCAL VOC2007</annotation>
    </source>
    <size>
        <width>512</width>
        <height>512</height>
        <depth>3</depth>
    </size>
    <object>
        <name>Character</name>
        <occluded>0</occluded>
        <bndbox>
            <xmin>6</xmin>
            <ymin>36</ymin>
            <xmax>75</xmax>
            <ymax>110</ymax>
        </bndbox>
    </object>
    <object>
        <name>Character</name>
        <occluded>0</occluded>
        <bndbox>
            <xmin>98</xmin>
            <ymin>38</ymin>
            <xmax>151</xmax>
            <ymax>108</ymax>
        </bndbox>
    </object>
    <object>
        <name>Character</name>
        <occluded>0</occluded>
        <bndbox>
            <xmin>152</xmin>
            <ymin>38</ymin>
            <xmax>218</xmax>
            <ymax>106</ymax>
        </bndbox>
    </object>
    <object>
        <name>Character</name>
        <occluded>0</occluded>
        <bndbox>
            <xmin>220</xmin>
            <ymin>41</ymin>
            <xmax>284</xmax>
            <ymax>105</ymax>
        </bndbox>
    </object>
    <object>
        <name>Character</name>
        <occluded>0</occluded>
        <bndbox>
            <xmin>286</xmin>
            <ymin>37</ymin>
            <xmax>352</xmax>
            <ymax>110</ymax>
        </bndbox>
    </object>
    <object>
        <name>Character</name>
        <occluded>0</occluded>
        <bndbox>
            <xmin>354</xmin>
            <ymin>40</ymin>
            <xmax>425</xmax>
            <ymax>108</ymax>
        </bndbox>
    </object>
    <object>
        <name>Character</name>
        <occluded>0</occluded>
        <bndbox>
            <xmin>428</xmin>
            <ymin>39</ymin>
            <xmax>495</xmax>
            <ymax>113</ymax>
        </bndbox>
    </object>
    <object>
        <name>Character</name>
        <occluded>0</occluded>
        <bndbox>
            <xmin>122</xmin>
            <ymin>118</ymin>
            <xmax>186</xmax>
            <ymax>190</ymax>
        </bndbox>
    </object>
    <object>
        <name>Character</name>
        <occluded>0</occluded>
        <bndbox>
            <xmin>190</xmin>
            <ymin>119</ymin>
            <xmax>250</xmax>
            <ymax>192</ymax>
        </bndbox>
    </object>
    <object>
        <name>Character</name>
        <occluded>0</occluded>
        <bndbox>
            <xmin>248</xmin>
            <ymin>119</ymin>
            <xmax>312</xmax>
            <ymax>192</ymax>
        </bndbox>
    </object>
    <object>
        <name>Character</name>
        <occluded>0</occluded>
        <bndbox>
            <xmin>311</xmin>
            <ymin>120</ymin>
            <xmax>381</xmax>
            <ymax>189</ymax>
        </bndbox>
    </object>
</annotation>
