<?xml version="1.0" encoding="UTF-8"?>
<annotation>
    <folder>ar0001_kakaku_kB0000151557.jpg</folder>
    <filename>003276.jpg</filename>
    <source>
        <database>The VOC2007 Database</database>
        <annotation>PASCAL VOC2007</annotation>
    </source>
    <size>
        <width>512</width>
        <height>512</height>
        <depth>3</depth>
    </size>
    <object>
        <name>Character</name>
        <occluded>0</occluded>
        <bndbox>
            <xmin>14</xmin>
            <ymin>14</ymin>
            <xmax>190</xmax>
            <ymax>162</ymax>
        </bndbox>
    </object>
    <object>
        <name>Character</name>
        <occluded>0</occluded>
        <bndbox>
            <xmin>318</xmin>
            <ymin>13</ymin>
            <xmax>489</xmax>
            <ymax>166</ymax>
        </bndbox>
    </object>
</annotation>
