<?xml version="1.0" encoding="UTF-8"?>
<annotation>
    <folder>ar0001_kakaku_kB0000151761.jpg</folder>
    <filename>003318.jpg</filename>
    <source>
        <database>The VOC2007 Database</database>
        <annotation>PASCAL VOC2007</annotation>
    </source>
    <size>
        <width>512</width>
        <height>512</height>
        <depth>3</depth>
    </size>
    <object>
        <name>Character</name>
        <occluded>0</occluded>
        <bndbox>
            <xmin>11</xmin>
            <ymin>147</ymin>
            <xmax>37</xmax>
            <ymax>166</ymax>
        </bndbox>
    </object>
    <object>
        <name>Character</name>
        <occluded>0</occluded>
        <bndbox>
            <xmin>37</xmin>
            <ymin>150</ymin>
            <xmax>59</xmax>
            <ymax>166</ymax>
        </bndbox>
    </object>
    <object>
        <name>Character</name>
        <occluded>0</occluded>
        <bndbox>
            <xmin>63</xmin>
            <ymin>149</ymin>
            <xmax>86</xmax>
            <ymax>168</ymax>
        </bndbox>
    </object>
    <object>
        <name>Character</name>
        <occluded>0</occluded>
        <bndbox>
            <xmin>90</xmin>
            <ymin>148</ymin>
            <xmax>114</xmax>
            <ymax>167</ymax>
        </bndbox>
    </object>
    <object>
        <name>Character</name>
        <occluded>0</occluded>
        <bndbox>
            <xmin>118</xmin>
            <ymin>149</ymin>
            <xmax>138</xmax>
            <ymax>167</ymax>
        </bndbox>
    </object>
    <object>
        <name>Character</name>
        <occluded>0</occluded>
        <bndbox>
            <xmin>142</xmin>
            <ymin>148</ymin>
            <xmax>159</xmax>
            <ymax>166</ymax>
        </bndbox>
    </object>
    <object>
        <name>Character</name>
        <occluded>0</occluded>
        <bndbox>
            <xmin>163</xmin>
            <ymin>148</ymin>
            <xmax>188</xmax>
            <ymax>168</ymax>
        </bndbox>
    </object>
    <object>
        <name>Character</name>
        <occluded>0</occluded>
        <bndbox>
            <xmin>191</xmin>
            <ymin>149</ymin>
            <xmax>216</xmax>
            <ymax>168</ymax>
        </bndbox>
    </object>
    <object>
        <name>Character</name>
        <occluded>0</occluded>
        <bndbox>
            <xmin>219</xmin>
            <ymin>148</ymin>
            <xmax>240</xmax>
            <ymax>168</ymax>
        </bndbox>
    </object>
    <object>
        <name>Character</name>
        <occluded>0</occluded>
        <bndbox>
            <xmin>243</xmin>
            <ymin>149</ymin>
            <xmax>263</xmax>
            <ymax>166</ymax>
        </bndbox>
    </object>
    <object>
        <name>Character</name>
        <occluded>0</occluded>
        <bndbox>
            <xmin>266</xmin>
            <ymin>150</ymin>
            <xmax>288</xmax>
            <ymax>166</ymax>
        </bndbox>
    </object>
    <object>
        <name>Character</name>
        <occluded>0</occluded>
        <bndbox>
            <xmin>293</xmin>
            <ymin>151</ymin>
            <xmax>307</xmax>
            <ymax>165</ymax>
        </bndbox>
    </object>
    <object>
        <name>Character</name>
        <occluded>0</occluded>
        <bndbox>
            <xmin>309</xmin>
            <ymin>149</ymin>
            <xmax>332</xmax>
            <ymax>165</ymax>
        </bndbox>
    </object>
    <object>
        <name>Character</name>
        <occluded>0</occluded>
        <bndbox>
            <xmin>7</xmin>
            <ymin>170</ymin>
            <xmax>50</xmax>
            <ymax>204</ymax>
        </bndbox>
    </object>
    <object>
        <name>Character</name>
        <occluded>0</occluded>
        <bndbox>
            <xmin>51</xmin>
            <ymin>171</ymin>
            <xmax>86</xmax>
            <ymax>204</ymax>
        </bndbox>
    </object>
    <object>
        <name>Character</name>
        <occluded>0</occluded>
        <bndbox>
            <xmin>88</xmin>
            <ymin>178</ymin>
            <xmax>123</xmax>
            <ymax>202</ymax>
        </bndbox>
    </object>
    <object>
        <name>Character</name>
        <occluded>0</occluded>
        <bndbox>
            <xmin>123</xmin>
            <ymin>172</ymin>
            <xmax>149</xmax>
            <ymax>203</ymax>
        </bndbox>
    </object>
    <object>
        <name>Character</name>
        <occluded>0</occluded>
        <bndbox>
            <xmin>150</xmin>
            <ymin>178</ymin>
            <xmax>184</xmax>
            <ymax>202</ymax>
        </bndbox>
    </object>
    <object>
        <name>Character</name>
        <occluded>0</occluded>
        <bndbox>
            <xmin>187</xmin>
            <ymin>179</ymin>
            <xmax>219</xmax>
            <ymax>202</ymax>
        </bndbox>
    </object>
    <object>
        <name>Character</name>
        <occluded>0</occluded>
        <bndbox>
            <xmin>222</xmin>
            <ymin>169</ymin>
            <xmax>254</xmax>
            <ymax>203</ymax>
        </bndbox>
    </object>
    <object>
        <name>Character</name>
        <occluded>0</occluded>
        <bndbox>
            <xmin>258</xmin>
            <ymin>180</ymin>
            <xmax>292</xmax>
            <ymax>201</ymax>
        </bndbox>
    </object>
    <object>
        <name>Character</name>
        <occluded>0</occluded>
        <bndbox>
            <xmin>294</xmin>
            <ymin>177</ymin>
            <xmax>329</xmax>
            <ymax>208</ymax>
        </bndbox>
    </object>
    <object>
        <name>Character</name>
        <occluded>0</occluded>
        <bndbox>
            <xmin>7</xmin>
            <ymin>210</ymin>
            <xmax>59</xmax>
            <ymax>243</ymax>
        </bndbox>
    </object>
    <object>
        <name>Character</name>
        <occluded>0</occluded>
        <bndbox>
            <xmin>61</xmin>
            <ymin>205</ymin>
            <xmax>116</xmax>
            <ymax>242</ymax>
        </bndbox>
    </object>
    <object>
        <name>Character</name>
        <occluded>0</occluded>
        <bndbox>
            <xmin>120</xmin>
            <ymin>205</ymin>
            <xmax>173</xmax>
            <ymax>245</ymax>
        </bndbox>
    </object>
    <object>
        <name>Character</name>
        <occluded>0</occluded>
        <bndbox>
            <xmin>178</xmin>
            <ymin>203</ymin>
            <xmax>228</xmax>
            <ymax>245</ymax>
        </bndbox>
    </object>
    <object>
        <name>Character</name>
        <occluded>0</occluded>
        <bndbox>
            <xmin>232</xmin>
            <ymin>206</ymin>
            <xmax>279</xmax>
            <ymax>246</ymax>
        </bndbox>
    </object>
    <object>
        <name>Character</name>
        <occluded>0</occluded>
        <bndbox>
            <xmin>280</xmin>
            <ymin>209</ymin>
            <xmax>332</xmax>
            <ymax>245</ymax>
        </bndbox>
    </object>
</annotation>
