<?xml version="1.0" encoding="UTF-8"?>
<annotation>
    <folder>ar0001_kakaku_kB0000236844.jpg</folder>
    <filename>004449.jpg</filename>
    <source>
        <database>The VOC2007 Database</database>
        <annotation>PASCAL VOC2007</annotation>
    </source>
    <size>
        <width>512</width>
        <height>512</height>
        <depth>3</depth>
    </size>
    <object>
        <name>Character</name>
        <occluded>0</occluded>
        <bndbox>
            <xmin>25</xmin>
            <ymin>15</ymin>
            <xmax>98</xmax>
            <ymax>70</ymax>
        </bndbox>
    </object>
    <object>
        <name>Character</name>
        <occluded>0</occluded>
        <bndbox>
            <xmin>104</xmin>
            <ymin>16</ymin>
            <xmax>175</xmax>
            <ymax>69</ymax>
        </bndbox>
    </object>
    <object>
        <name>Character</name>
        <occluded>0</occluded>
        <bndbox>
            <xmin>178</xmin>
            <ymin>31</ymin>
            <xmax>231</xmax>
            <ymax>66</ymax>
        </bndbox>
    </object>
    <object>
        <name>Character</name>
        <occluded>0</occluded>
        <bndbox>
            <xmin>72</xmin>
            <ymin>69</ymin>
            <xmax>150</xmax>
            <ymax>123</ymax>
        </bndbox>
    </object>
    <object>
        <name>Character</name>
        <occluded>0</occluded>
        <bndbox>
            <xmin>154</xmin>
            <ymin>71</ymin>
            <xmax>226</xmax>
            <ymax>123</ymax>
        </bndbox>
    </object>
</annotation>
